FTPS3/FTPtoS3.py
FTPS3/__init__.py
FTPtoS3-0.1.2.dist-info/LICENSE.md
FTPtoS3-0.1.2.dist-info/METADATA
FTPtoS3-0.1.2.dist-info/WHEEL
FTPtoS3-0.1.2.dist-info/top_level.txt
FTPtoS3-0.1.2.dist-info/RECORD
