Metadata-Version: 2.1
Name: FTPtoS3
Version: 0.1.2
Summary: Package for transferring huge files from FTP to S3
Home-page: https://github.com/Deep-Mind-Hive/FTPS3
Author: Harsh Vardhan and Sai Madhav
Author-email: deephivemind@gmail.com,kambhampati.sm@gmail.com
License: UNKNOWN
Keywords: FTPS3,ftptos3,data migrate from FTP to S3
Platform: UNKNOWN
Classifier: License :: OSI Approved :: MIT License
Classifier: Operating System :: OS Independent
Classifier: Programming Language :: Python
Classifier: Programming Language :: Python :: 3 :: Only
Classifier: Programming Language :: Python :: 3.5
Classifier: Programming Language :: Python :: 3.6
Classifier: Programming Language :: Python :: 3.7
Classifier: Programming Language :: Python :: 3.8
Classifier: Programming Language :: Python :: 3.9
Classifier: Programming Language :: Python :: 3.10
Requires-Python: >=3.5, <4
License-File: LICENSE.md
Requires-Dist: ftplib
Requires-Dist: boto3
